README.rst
setup.py
autopilothq/__init__.py
autopilothq.egg-info/PKG-INFO
autopilothq.egg-info/SOURCES.txt
autopilothq.egg-info/dependency_links.txt
autopilothq.egg-info/top_level.txt