Metadata-Version: 1.0
Name: autopilothq
Version: 0.0.1
Summary: Wrapper to the autopilothq.com REST API
Home-page: UNKNOWN
Author: UNKNOWN
Author-email: UNKNOWN
License: MIT
Platform: UNKNOWN
